m21ctools/config.py
m21ctools/data_handler.py
m21ctools/plot_example.py
m21ctools-0.2.0.dist-info/METADATA
m21ctools-0.2.0.dist-info/WHEEL
m21ctools-0.2.0.dist-info/licenses/LICENSE
m21ctools-0.2.0.dist-info/RECORD
