Metadata-Version: 2.4
Name: m21ctools
Version: 0.2.0
Summary: Tools for processing cubed-sphere data.
Project-URL: Homepage, https://github.com/ftgoktas/m21ctools
Author-email: Sabin Adhikari <sbn.adh@gmail.com>, Furkan Goktas <ftgoktas@gmail.com>
License: MIT
License-File: LICENSE
Requires-Dist: cartopy
Requires-Dist: dask
Requires-Dist: icechunk
Requires-Dist: matplotlib
Requires-Dist: numpy
Requires-Dist: scipy
Requires-Dist: xarray
